{
    "title": "GIT",
    "content": [
        {
            "name": "Introduccion",
            "description": "¿Qué es?, ¿Para qué sirve?",
            "links": [
                { "key": "", "href": "" },
                { "key": "", "href": "" }
            ]
        },
        {
            "name": "Uso basico",
            "description": "Working directory-Stage-Head, Commit, Log",
            "links": [
                { "key": "", "href": "" },
                { "key": "", "href": "" }
            ]
        },
        {
            "name": "Uso colaborativo",
            "description": "Branchs - Merge, Remotes(Github-Gitlab), Push, Pull-Fetch, Clone",
            "links": [
                { "key": "", "href": "" },
                { "key": "", "href": "" }
            ]
        },
        {
            "name": "",
            "void": true
        }
    ]
}
