{
    "course": {
        "name same of url": {
            "title": "name of course",
            "description": "description of course",
            "telegram": "url to telegram",
            "url": "/name",
            "content": [
                {
                    "name": "name of content",
                    "description": "questions, topics and more of content",
                    "links": [
                        { "key": "visible name of link", "href": "url of link", "class": "type of link" },
                        { "key": "...", "href": "...", "class": "" }
                    ]
                },
                { 
                    "name": "",
                    "void": true
                }
            ]
        },
        "same of url": {
            "title": "name of course",
            "description": "description of course",
            "telegram": "url to telegram",
            "url": "/name",
            "content": [
                {
                    "title": "name of course",
                    "content": [
                        {
                            "name": "name of content",
                            "description": "questions, topics and more of content",
                            "links": [
                                { "key": "visible name of link", "href": "url of link", "class": "type of link" },
                                { "key": "...", "href": "...", "class": "" }
                            ]
                        },
                        {
                            "name": "",
                            "void": true
                        }
                    ]
                }
            ]
        },
        "types of link": [
            "video", 
            "exercise",
            "documentation"
        ]
    }
}
